dlt_providers/__init__.py
dlt_providers/helpers.py
dlt_providers/sources/__init__.py
dlt_providers/sources/github/README.md
dlt_providers/sources/github/__init__.py
dlt_providers/sources/github/helpers.py
dlt_providers/sources/github/settings.py
dlt_providers/sources/jira/README.md
dlt_providers/sources/jira/__init__.py
dlt_providers/sources/jira/settings.py
dlt_providers/sources/mysql_replication/__init__.py
dlt_providers/sources/mysql_replication/constants.py
dlt_providers/sources/mysql_replication/exceptions.py
dlt_providers/sources/mysql_replication/helpers.py
dlt_providers/sources/mysql_replication/schema_types.py
dlt_providers/sources/pg_replication/README.md
dlt_providers/sources/pg_replication/__init__.py
dlt_providers/sources/pg_replication/constants.py
dlt_providers/sources/pg_replication/decoders.py
dlt_providers/sources/pg_replication/exceptions.py
dlt_providers/sources/pg_replication/helpers.py
dlt_providers/sources/pg_replication/schema_types.py
dlt_providers-202601.13.0.dist-info/WHEEL
dlt_providers-202601.13.0.dist-info/METADATA
dlt_providers-202601.13.0.dist-info/RECORD
