Metadata-Version: 2.3
Name: dlt-providers
Version: 202601.13.0
Summary: Providers for data load tool (dlt)
Requires-Dist: dlt>=1.20.0,<1.21.0
Requires-Dist: connectorx
Requires-Dist: pyarrow
Requires-Dist: mysql-replication==0.46.0 ; extra == 'mysql-replication'
Requires-Dist: cryptography ; extra == 'mysql-replication'
Requires-Dist: plpygis ; extra == 'mysql-replication'
Requires-Dist: psycopg2-binary ; extra == 'pg-replication'
Requires-Python: >=3.10
Provides-Extra: mysql-replication
Provides-Extra: pg-replication
